cts3_viewer/AdvancedMeas.py
cts3_viewer/DaqMeas.py
cts3_viewer/Meas.py
cts3_viewer/SpyMeas.py
cts3_viewer/__init__.py
cts3_viewer/__main__.py
cts3_viewer-24.1.0.dist-info/LICENSE
cts3_viewer-24.1.0.dist-info/METADATA
cts3_viewer-24.1.0.dist-info/WHEEL
cts3_viewer-24.1.0.dist-info/entry_points.txt
cts3_viewer-24.1.0.dist-info/top_level.txt
cts3_viewer-24.1.0.dist-info/RECORD
