Metadata-Version: 2.1
Name: cts3-viewer
Version: 24.1.0
Summary: CTS3 Waveform Viewer
Author-email: Julien Vannier <julien.m.vannier@gmail.com>
Maintainer-email: Guillaume Fouilleul <guillaume.fouilleul@gmail.com>
License: MIT
Project-URL: Homepage, https://www.fime.com/shop/product/contactless-test-station-cts-iii-41
Project-URL: Download, https://pypi.org/project/cts3-viewer
Project-URL: Code, https://github.com/Micropross/CTS3_viewer
Keywords: NI,FIME,CTS3,NFC
Platform: any
Classifier: Development Status :: 5 - Production/Stable
Classifier: Intended Audience :: Developers
Classifier: Intended Audience :: Education
Classifier: Intended Audience :: Science/Research
Classifier: License :: OSI Approved :: MIT License
Classifier: Natural Language :: English
Classifier: Operating System :: Microsoft :: Windows
Classifier: Operating System :: MacOS :: MacOS X
Classifier: Operating System :: POSIX :: Linux
Classifier: Programming Language :: Python :: 3
Classifier: Programming Language :: Python :: 3 :: Only
Classifier: Programming Language :: Python :: 3.9
Classifier: Programming Language :: Python :: 3.10
Classifier: Programming Language :: Python :: 3.11
Classifier: Programming Language :: Python :: 3.12
Classifier: Programming Language :: Python :: 3.13
Classifier: Topic :: Scientific/Engineering :: Visualization
Requires-Python: >=3.9
License-File: LICENSE
Requires-Dist: numpy >=1.21
Requires-Dist: plotly >=4.0
